README.md
setup.py
keeper_secrets_manager_ansible/__init__.py
keeper_secrets_manager_ansible/__main__.py
keeper_secrets_manager_ansible.egg-info/PKG-INFO
keeper_secrets_manager_ansible.egg-info/SOURCES.txt
keeper_secrets_manager_ansible.egg-info/dependency_links.txt
keeper_secrets_manager_ansible.egg-info/entry_points.txt
keeper_secrets_manager_ansible.egg-info/not-zip-safe
keeper_secrets_manager_ansible.egg-info/requires.txt
keeper_secrets_manager_ansible.egg-info/top_level.txt
keeper_secrets_manager_ansible/plugins/__init__.py
keeper_secrets_manager_ansible/plugins/action/__init__.py
keeper_secrets_manager_ansible/plugins/action/keeper_cache_records.py
keeper_secrets_manager_ansible/plugins/action/keeper_cleanup.py
keeper_secrets_manager_ansible/plugins/action/keeper_copy.py
keeper_secrets_manager_ansible/plugins/action/keeper_create.py
keeper_secrets_manager_ansible/plugins/action/keeper_get.py
keeper_secrets_manager_ansible/plugins/action/keeper_get_record.py
keeper_secrets_manager_ansible/plugins/action/keeper_info.py
keeper_secrets_manager_ansible/plugins/action/keeper_init.py
keeper_secrets_manager_ansible/plugins/action/keeper_password.py
keeper_secrets_manager_ansible/plugins/action/keeper_remove.py
keeper_secrets_manager_ansible/plugins/action/keeper_set.py
keeper_secrets_manager_ansible/plugins/cache/__init__.py
keeper_secrets_manager_ansible/plugins/callback/__init__.py
keeper_secrets_manager_ansible/plugins/callback/keeper_redact.py
keeper_secrets_manager_ansible/plugins/filter/__init__.py
keeper_secrets_manager_ansible/plugins/inventory/__init__.py
keeper_secrets_manager_ansible/plugins/lookup/__init__.py
keeper_secrets_manager_ansible/plugins/lookup/keeper.py
keeper_secrets_manager_ansible/plugins/module_utils/__init__.py
keeper_secrets_manager_ansible/plugins/modules/__init__.py
keeper_secrets_manager_ansible/plugins/modules/keeper_cache_records.py
keeper_secrets_manager_ansible/plugins/modules/keeper_cleanup.py
keeper_secrets_manager_ansible/plugins/modules/keeper_copy.py
keeper_secrets_manager_ansible/plugins/modules/keeper_create.py
keeper_secrets_manager_ansible/plugins/modules/keeper_get.py
keeper_secrets_manager_ansible/plugins/modules/keeper_get_record.py
keeper_secrets_manager_ansible/plugins/modules/keeper_info.py
keeper_secrets_manager_ansible/plugins/modules/keeper_init.py
