Metadata-Version: 2.4
Name: keeper-secrets-manager-ansible
Version: 1.2.6
Summary: Keeper Secrets Manager plugins for Ansible.
Home-page: https://github.com/Keeper-Security/secrets-manager
Author: Keeper Security
Author-email: ops@keepersecurity.com
License: MIT
Project-URL: Bug Tracker, https://github.com/Keeper-Security/secrets-manager/issues
Project-URL: Documentation, https://app.gitbook.com/@keeper-security/s/secrets-manager/secrets-manager/integrations/ansible-plugin
Project-URL: Source Code, https://github.com/Keeper-Security/secrets-manager
Keywords: Keeper Secrets Manager SDK Ansible
Classifier: Development Status :: 5 - Production/Stable
Classifier: Intended Audience :: Developers
Classifier: Intended Audience :: System Administrators
Classifier: License :: OSI Approved :: MIT License
Classifier: Operating System :: OS Independent
Classifier: Programming Language :: Python
Classifier: Programming Language :: Python :: 3
Classifier: Programming Language :: Python :: 3.7
Classifier: Programming Language :: Python :: 3.8
Classifier: Programming Language :: Python :: 3.9
Classifier: Programming Language :: Python :: 3.10
Classifier: Programming Language :: Python :: 3.11
Classifier: Topic :: Security
Classifier: Topic :: System :: Installation/Setup
Classifier: Topic :: System :: Systems Administration
Requires-Python: >=3.7
Requires-Dist: keeper-secrets-manager-core>=16.6.6
Requires-Dist: keeper-secrets-manager-helper>=1.0.5
Requires-Dist: importlib_metadata
Requires-Dist: ansible-core>=2.12.0
Dynamic: author
Dynamic: author-email
Dynamic: classifier
Dynamic: description
Dynamic: description-content-type
Dynamic: home-page
Dynamic: keywords
Dynamic: license
Dynamic: project-url
Dynamic: requires-dist
Dynamic: requires-python
Dynamic: summary
